layer_builder/__init__.py
layer_builder-0.1.1.dist-info/METADATA
layer_builder-0.1.1.dist-info/WHEEL
layer_builder-0.1.1.dist-info/RECORD
