Metadata-Version: 2.4
Name: layer-builder
Version: 0.1.1
Summary: Enables building AWS Lambda Layers from requirement files as part of CDK deployments
License: MIT
Author: dschultz0
Author-email: dave@daveschultzconsulting.com
Requires-Python: >=3.10,<4.0
Classifier: License :: OSI Approved :: MIT License
Classifier: Programming Language :: Python :: 3
Classifier: Programming Language :: Python :: 3.10
Classifier: Programming Language :: Python :: 3.11
Classifier: Programming Language :: Python :: 3.12
Classifier: Programming Language :: Python :: 3.13
Classifier: Programming Language :: Python :: 3.14
